{
    "All": [
        50,
        158717543
    ],
    "Pop": [
        50,
        157957715
    ],
    "Rap/Hip Hop": [
        50,
        64400269
    ],
    "Rock": [
        49,
        79974006
    ],
    "Dance": [
        50,
        92272435
    ],
    "R&B": [
        50,
        43602038
    ],
    "Alternative": [
        50,
        74506846
    ],
    "Electro": [
        49,
        22531247
    ],
    "Folk": [
        46,
        2359523
    ],
    "Reggae": [
        48,
        24147472
    ],
    "Jazz": [
        50,
        13593762
    ],
    "Classical": [
        49,
        6193489
    ],
    "Films/Games": [
        49,
        9909770
    ],
    "Metal": [
        50,
        17949476
    ],
    "Soul & Funk": [
        48,
        6361393
    ],
    "African Music": [
        36,
        1369948
    ],
    "Asian Music": [
        50,
        5838898
    ],
    "Blues": [
        48,
        7257733
    ],
    "Brazilian Music": [
        50,
        54747613
    ],
    "Indian Music": [
        2,
        4010
    ],
    "Kids": [
        36,
        22166539
    ],
    "Latin Music": [
        50,
        56833316
    ],
    "Musique russe": [
        0,
        0
    ]
}